knmy/__init__.py
knmy/knmy.py
knmy/parser.py
knmy-1.5.1.dist-info/LICENSE.md
knmy-1.5.1.dist-info/METADATA
knmy-1.5.1.dist-info/WHEEL
knmy-1.5.1.dist-info/top_level.txt
knmy-1.5.1.dist-info/RECORD
