Metadata-Version: 2.1
Name: knmy
Version: 1.5.1
Summary: Python package for downloading and processing weather data from the automated weather stations of the Dutch Meteorological Institute (KNMI).
Home-page: https://github.com/barthoekstra/knmy
Download-URL: https://github.com/barthoekstra/knmy/tarball/1.5.1
Author: Bart Hoekstra
Author-email: Bart Hoekstra <barthoekstra@gmail.com>
License: Copyright (c) 2022, Bart Hoekstra
Project-URL: Homepage, https://github.com/barthoekstra/knmy
Project-URL: Bug Tracker, https://github.com/barthoekstra/knmy//issues
Classifier: Programming Language :: Python :: 3
Classifier: License :: OSI Approved :: BSD License
Classifier: Operating System :: OS Independent
Requires-Python: >=3.4
License-File: LICENSE.md
Requires-Dist: sphinx
Requires-Dist: sphinx-rtd-theme
Requires-Dist: pytest
Requires-Dist: requests
Requires-Dist: pandas
